mlcube_docker/__init__.py
mlcube_docker/__main__.py
mlcube_docker/docker_run.py
mlcube_docker/tests/__init__.py
mlcube_docker/tests/test_config.py
mlcube_docker/tests/test_docker_runner.py
mlcube_docker/tests/test_factory_fn.py
mlcube_docker-0.0.9.dist-info/METADATA
mlcube_docker-0.0.9.dist-info/WHEEL
mlcube_docker-0.0.9.dist-info/entry_points.txt
mlcube_docker-0.0.9.dist-info/top_level.txt
mlcube_docker-0.0.9.dist-info/RECORD
